cdk_eks_blueprint/__init__.py
cdk_eks_blueprint/addons/__init__.py
cdk_eks_blueprint/cluster/__init__.py
cdk_eks_blueprint/cluster/_params_validation.py
cdk_eks_blueprint/cluster/controller_plane.py
cdk_eks_blueprint/cluster/eks_cluster.py
cdk_eks_blueprint/cluster/fargate_profile.py
cdk_eks_blueprint/cluster/managed_node_group.py
cdk_eks_blueprint/cluster/self_managed_node_group.py
cdk_eks_blueprint-0.0.10.dist-info/LICENSE
cdk_eks_blueprint-0.0.10.dist-info/METADATA
cdk_eks_blueprint-0.0.10.dist-info/WHEEL
cdk_eks_blueprint-0.0.10.dist-info/top_level.txt
cdk_eks_blueprint-0.0.10.dist-info/RECORD
