Metadata-Version: 2.1
Name: cdk-eks-blueprint
Version: 0.0.10
Summary: Amazon EKS Blueprint for CDK Python
Author-email: leunguu <liangy3928@gmail.com>
License: MIT
Project-URL: homepage, https://github.com/LEUNGUU/cdk-eks-blueprint
Project-URL: repository, https://github.com/LEUNGUU/cdk-eks-blueprint.git
Keywords: CDK,EKS,Python,IaC,Blueprint
Classifier: Programming Language :: Python :: 3
Classifier: License :: OSI Approved :: MIT License
Classifier: Operating System :: OS Independent
Requires-Python: >=3.10
License-File: LICENSE
Requires-Dist: semver
Requires-Dist: aws-cdk-lib (<3.0.0,>=2.1.0)
Requires-Dist: constructs (<11.0.0,>=10.0.5)
Requires-Dist: aws-cdk.lambda-layer-kubectl-v24
